psycopg2/__init__.py
psycopg2/_ipaddress.py
psycopg2/_json.py
psycopg2/_lru_cache.py
psycopg2/_psycopg.cpython-37m-x86_64-linux-gnu.so
psycopg2/_range.py
psycopg2/compat.py
psycopg2/errorcodes.py
psycopg2/errors.py
psycopg2/extensions.py
psycopg2/extras.py
psycopg2/pool.py
psycopg2/sql.py
psycopg2/tz.py
test_psycopg2-2.8.5.dist-info/LICENSE
test_psycopg2-2.8.5.dist-info/METADATA
test_psycopg2-2.8.5.dist-info/WHEEL
test_psycopg2-2.8.5.dist-info/top_level.txt
test_psycopg2-2.8.5.dist-info/RECORD
